{
  "阿铎": {
    "aliases": [
      "阿铎"
    ],
    "fragments": [
      "大多是礼貌性的点赞和转发，但有一条留言引起了他的注意，一个叫\"阿铎\"的人写道：\"念真姐，上次说的录音设备我下周可以带过来试试，但我月底要跟乐队去福州演出"
    ]
  },
  "阿衍": {
    "aliases": [
      "阿衍"
    ],
    "fragments": [
      "\"阿衍跟我提过，说你回来了，要拍东西",
      "\"她说，\"因为阿衍跟我说你这次是认真的",
      "回去的公交车上，沈屿白把素材粗略翻了一遍，挑出十几张发给阿衍",
      "阿衍的回复来得很快，先是一个放大的表情，然后是一条语音",
      "沈屿白点开，阿衍的声音带着没睡醒的鼻音：\"构图不错，光也好，但你这个叙事线还是太散了",
      "阿衍说得对",
      "是阿衍追加的一条消息：\"另外，你要是认真的，光手持不行",
      "阿衍你知道的，还在这儿晃",
      "沈屿白在阿衍走后独自坐在出租屋里，对着手机通讯录翻了很久",
      "我在筹备一个独立短片项目，拍澜城老渔港那边的题材，阿衍已经答应做摄影了，但我们缺机器"
    ]
  },
  "老周": {
    "aliases": [
      "老周"
    ],
    "fragments": [
      "\"她的语气很平，像在说一件与自己无关的事，\"老周你还记得吧，管灯光的那个他搬了最后一箱黑胶出来，蹲在路边哭",
      "\"许念真靠回椅背，双手交叠放在腿上，\"老周去了杭州，做舞台灯光租赁"
    ]
  },
  "小鹿": {
    "aliases": [
      "小鹿"
    ],
    "fragments": [
      "小鹿考了编制，在区文化馆上班，偶尔帮社区排节目"
    ]
  }
}